og_discord/__init__.py
og_discord/discord_chat.py
og_terminal/__init__.py
og_terminal/markdown.py
og_terminal/ping.py
og_terminal/terminal_chat.py
og_terminal/ui_block.py
og_terminal/utils.py
og_chat-0.5.3.dist-info/METADATA
og_chat-0.5.3.dist-info/WHEEL
og_chat-0.5.3.dist-info/entry_points.txt
og_chat-0.5.3.dist-info/top_level.txt
og_chat-0.5.3.dist-info/RECORD
