Metadata-Version: 2.1
Name: og-chat
Version: 0.5.3
Summary: the chat client for open source code interpreter octogen
Home-page: https://github.com/dbpunk-labs/octogen
Author: imotai
Author-email: codego.me@gmail.com
Requires-Dist: og-sdk >=0.1.0
Requires-Dist: rich >=13.5.2
Requires-Dist: prompt-toolkit >=3.0.0
Requires-Dist: click >=8.0.0
Requires-Dist: discord.py >=2.3.2
Requires-Dist: clipboard >=0.0.4
Requires-Dist: term-image >=0.7.0
Requires-Dist: python-dotenv
